setup.py
wip_hello_world/__init__.py
wip_hello_world.egg-info/PKG-INFO
wip_hello_world.egg-info/SOURCES.txt
wip_hello_world.egg-info/dependency_links.txt
wip_hello_world.egg-info/not-zip-safe
wip_hello_world.egg-info/top_level.txt