Metadata-Version: 1.0
Name: wip-hello-world
Version: 0.1
Summary: Simple hello world
Home-page: UNKNOWN
Author: Hugo
Author-email: hugo@example.com
License: MIT
Platform: UNKNOWN
